cyvest/__init__.py
cyvest/cli.py
cyvest/compare.py
cyvest/cyvest.py
cyvest/investigation.py
cyvest/io_rich.py
cyvest/io_schema.py
cyvest/io_serialization.py
cyvest/io_visualization.py
cyvest/keys.py
cyvest/level_score_rules.py
cyvest/levels.py
cyvest/model.py
cyvest/model_enums.py
cyvest/model_schema.py
cyvest/proxies.py
cyvest/score.py
cyvest/shared.py
cyvest/stats.py
cyvest/ulid.py
cyvest-5.1.4.dist-info/WHEEL
cyvest-5.1.4.dist-info/entry_points.txt
cyvest-5.1.4.dist-info/METADATA
cyvest-5.1.4.dist-info/RECORD
