Metadata-Version: 2.3
Name: cyvest
Version: 5.1.4
Summary: Cybersecurity investigation model
Keywords: cybersecurity,investigation,threat-intel,security-analysis
Author: PakitoSec
Author-email: PakitoSec <jeromep83@gmail.com>
License: MIT
Classifier: Development Status :: 4 - Beta
Classifier: Intended Audience :: Developers
Classifier: License :: OSI Approved :: MIT License
Classifier: Programming Language :: Python :: 3
Classifier: Programming Language :: Python :: 3.10
Classifier: Programming Language :: Python :: 3.11
Classifier: Programming Language :: Python :: 3.12
Classifier: Topic :: Security
Requires-Dist: click>=8
Requires-Dist: logurich[click]>=0.6.0
Requires-Dist: pydantic>=2.12.5
Requires-Dist: rich>=13
Requires-Dist: typing-extensions>=4.15
Requires-Dist: pyvis>=0.3.2 ; extra == 'visualization'
Requires-Python: >=3.10
Project-URL: Homepage, https://github.com/PakitoSec/cyvest
Project-URL: Repository, https://github.com/PakitoSec/cyvest
Project-URL: Issues, https://github.com/PakitoSec/cyvest/issues
Provides-Extra: visualization
